familylink/__init__.py
familylink/cli.py
familylink/client.py
familylink/models.py
familylink-0.1.8.dist-info/METADATA
familylink-0.1.8.dist-info/WHEEL
familylink-0.1.8.dist-info/entry_points.txt
familylink-0.1.8.dist-info/RECORD
