Metadata-Version: 2.4
Name: familylink
Version: 0.1.8
Summary: Add your description here
Author-email: Thibault Ducret <hello@tducret.com>
Requires-Python: >=3.10
Requires-Dist: browser-cookie3>=0.19.1
Requires-Dist: httpx>=0.28.1
Requires-Dist: pydantic>=1.8.2
Requires-Dist: rich>=13.7.0
